{
  "key": "google",
  "name": "Google",
  "icon": "google",
  "scopes": ["openid", "profile", "email"],
  "authorize_url": "https://accounts.google.com/o/oauth2/v2/auth",
  "access_url": "https://oauth2.googleapis.com/token",
  "profile_url": "https://openidconnect.googleapis.com/v1/userinfo",
  "profile_map": {
    "email": "email",
    "first_name": "given_name",
    "last_name": "family_name",
    "avatar": "picture",
    "locale": "locale"
  },
  "client_id": "602047752247-39qmihl9qoh15v24vr6ojptd5g60i9pr.apps.googleusercontent.com",
  "client_secret": "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"


}
